joao_marcionilo_finances/__init__.py
joao_marcionilo_finances/default_credential.py
joao_marcionilo_finances/models.py
joao_marcionilo_finances/server.py
joao_marcionilo_finances/system.py
joao_marcionilo_finances-0.1.0.dist-info/METADATA
joao_marcionilo_finances-0.1.0.dist-info/WHEEL
joao_marcionilo_finances-0.1.0.dist-info/licenses/LICENSE
joao_marcionilo_finances-0.1.0.dist-info/RECORD
