Metadata-Version: 2.4
Name: joao_marcionilo_finances
Version: 0.1.0
Summary: Package with CRUD using SQL Server and a FastAPI local server for testing it
Project-URL: Homepage, https://github.com/Joao-Marcionilo/finances
Author-email: João Marcionilo <marcionilojob@gmail.com>
License-File: LICENSE
Classifier: License :: OSI Approved :: MIT License
Classifier: Programming Language :: Python :: 3
Requires-Python: >=3.12
Requires-Dist: fastapi~=0.115.2
Requires-Dist: pydantic<2.0.0
Requires-Dist: pyodbc~=5.2.0
Requires-Dist: uvicorn~=0.32.0
